mt2gf/__init__.py
mt2gf/gform.py
mt2gf/mturk.py
mt2gf/preprocess.py
mt2gf/utils.py
mt2gf/watcher.py
mt2gf/widgets.py
mt2gf-0.1.3.dist-info/LICENSE.txt
mt2gf-0.1.3.dist-info/METADATA
mt2gf-0.1.3.dist-info/WHEEL
mt2gf-0.1.3.dist-info/top_level.txt
mt2gf-0.1.3.dist-info/RECORD
