Metadata-Version: 2.1
Name: mt2gf
Version: 0.1.3
Summary: UNKNOWN
Home-page: https://github.com/ymentha14/mturk2gform
Author: Yann Mentha
Author-email: yann.mentha@gmail.com
License: MIT
Platform: UNKNOWN
Requires-Python: >=3.6
Requires-Dist: setuptools (>=51.1.0)
Requires-Dist: jupyterlab (>=2.2.9)
Requires-Dist: ipykernel
Requires-Dist: pandas (>=1.1.2)
Requires-Dist: boto3 (>=1.16.25)
Requires-Dist: xmltodict (>=0.12.0)
Requires-Dist: google-auth (>=1.24.0)
Requires-Dist: google-api-python-client (>=1.12.8)
Requires-Dist: google-auth-oauthlib (>=0.4.2)
Requires-Dist: ipywidgets (>=7.5.1)
Requires-Dist: numpy (>=1.16.4)
Requires-Dist: tqdm (>=4.51.0)
Requires-Dist: python-Levenshtein (>=0.12.0)
